{
  "periodo": "Julho 2026",
  "hoje": {
    "vendas_valor": 46695.95,
    "vendas_qtd": 11,
    "atividades": 36
  },
  "comparativo": {
    "mes_anterior": {
      "nome": "Junho 2026",
      "total": 310032.65
    },
    "mes_atual": {
      "nome": "Julho 2026",
      "total": 176117.38
    }
  },
  "vendedoras": [
    {
      "iniciais": "GAB",
      "nome": "Gabriele",
      "classe": "ag",
      "cor1": "#6c63ff",
      "cor2": "#a855f7",
      "titulo": "Lider do Mes",
      "meta": 165000,
      "atividades": 86,
      "ganhos_qtd": 45,
      "ganhos_valor": 115114.42,
      "iniciados_qtd": 49,
      "iniciados_valor": 99897.86,
      "abertos_qtd": 10,
      "abertos_valor": 24874.41,
      "atrasados": 0,
      "perdidos_qtd": 11,
      "perdidos_valor": 49525.32,
      "conversao": 80.4,
      "atrasados_ok": true,
      "hoje_vendas_qtd": 4,
      "hoje_vendas_valor": 37782.38,
      "hoje_orcado_qtd": 2,
      "hoje_orcado_valor": 2153.91,
      "hoje_movimentacoes": 15,
      "hoje_atv_ligacao": 2,
      "hoje_atv_whatsapp": 2,
      "hoje_atv_email": 0,
      "hoje_atv_proposta": 0
    },
    {
      "iniciais": "ADR",
      "nome": "Adriane",
      "classe": "aa",
      "cor1": "#4facfe",
      "cor2": "#00f2fe",
      "titulo": "Vendedora",
      "meta": 165000,
      "atividades": 76,
      "ganhos_qtd": 47,
      "ganhos_valor": 61002.96,
      "iniciados_qtd": 56,
      "iniciados_valor": 111818.35,
      "abertos_qtd": 13,
      "abertos_valor": 71436.02,
      "atrasados": 0,
      "perdidos_qtd": 14,
      "perdidos_valor": 44541.07,
      "conversao": 77,
      "atrasados_ok": true,
      "hoje_vendas_qtd": 7,
      "hoje_vendas_valor": 8913.57,
      "hoje_orcado_qtd": 10,
      "hoje_orcado_valor": 30313.36,
      "hoje_movimentacoes": 21,
      "hoje_atv_ligacao": 0,
      "hoje_atv_whatsapp": 0,
      "hoje_atv_email": 0,
      "hoje_atv_proposta": 0
    }
  ],
  "funil": [
    {
      "etapa": "Fechamento",
      "qtd": 44,
      "valor": 114462.86,
      "conv": 100,
      "cor": "#6c63ff"
    },
    {
      "etapa": "Follow-up",
      "qtd": 37,
      "valor": 121885.51,
      "conv": 84.1,
      "cor": "#4facfe"
    },
    {
      "etapa": "Solicitação de Orçamento",
      "qtd": 29,
      "valor": 16617.95,
      "conv": 78.4,
      "cor": "#00d2b2"
    },
    {
      "etapa": "Envio de Proposta",
      "qtd": 15,
      "valor": 50661.57,
      "conv": 51.7,
      "cor": "#ffd60a"
    },
    {
      "etapa": "Negociação",
      "qtd": 2,
      "valor": 4398.75,
      "conv": 13.3,
      "cor": "#00ff95"
    },
    {
      "etapa": "Envio de Amostras",
      "qtd": 1,
      "valor": 0,
      "conv": 50,
      "cor": "#a855f7"
    }
  ],
  "motivos_perda": [
    {
      "label": "Preço Produto",
      "pct": 28,
      "cor": "#ff4d6d"
    },
    {
      "label": "Parou de Responder",
      "pct": 16,
      "cor": "#ff9e00"
    },
    {
      "label": "Comprou outra Marca",
      "pct": 16,
      "cor": "#ffd60a"
    },
    {
      "label": "Sem Previsão de Compra",
      "pct": 12,
      "cor": "#6c63ff"
    },
    {
      "label": "Prazo de Entrega",
      "pct": 8,
      "cor": "#4facfe"
    },
    {
      "label": "COMPROU COM A  TATO   + BARATO",
      "pct": 4,
      "cor": "#00d2b2"
    },
    {
      "label": "comprou na região devido a urgencia",
      "pct": 4,
      "cor": "#a855f7"
    }
  ],
  "atualizado_em": "2026-07-10T17:32:23.6878893-03:00"
}